stupidb/__init__.py
stupidb/aggregation.py
stupidb/aggregator.py
stupidb/api.py
stupidb/associative/__init__.py
stupidb/associative/animate.py
stupidb/associative/bitgraph.py
stupidb/associative/bitset.py
stupidb/associative/indextree.py
stupidb/associative/segmenttree.py
stupidb/core.py
stupidb/functions/__init__.py
stupidb/functions/associative/__init__.py
stupidb/functions/associative/core.py
stupidb/functions/navigation/__init__.py
stupidb/functions/navigation/core.py
stupidb/functions/ranking/__init__.py
stupidb/functions/ranking/core.py
stupidb/protocols.py
stupidb/row.py
stupidb/tests/__init__.py
stupidb/tests/conftest.py
stupidb/tests/test_animate.py
stupidb/tests/test_associative.py
stupidb/tests/test_bitgraph.py
stupidb/tests/test_bitset.py
stupidb/tests/test_index_tree.py
stupidb/tests/test_navigation.py
stupidb/tests/test_protocols.py
stupidb/tests/test_ranking.py
stupidb/tests/test_row.py
stupidb/tests/test_set_operations.py
stupidb/tests/test_stupidb.py
stupidb/typehints.py
stupidb-7.0.4.dist-info/LICENSE
stupidb-7.0.4.dist-info/WHEEL
stupidb-7.0.4.dist-info/METADATA
stupidb-7.0.4.dist-info/RECORD
