Metadata-Version: 2.1
Name: stupidb
Version: 7.0.4
Summary: The stupidest of all the databases.
Home-page: https://github.com/cpcloud/stupidb
License: Apache-2.0
Author: Phillip Cloud
Author-email: cpcloud@gmail.com
Maintainer: Phillip Cloud
Maintainer-email: cpcloud@gmail.com
Requires-Python: >=3.9,<3.11
Classifier: Development Status :: 2 - Pre-Alpha
Classifier: Intended Audience :: Developers
Classifier: License :: OSI Approved :: Apache Software License
Classifier: Natural Language :: English
Classifier: Programming Language :: Python :: 3
Classifier: Programming Language :: Python :: 3.10
Classifier: Programming Language :: Python :: 3.9
Provides-Extra: animation
Requires-Dist: atpublic (>=2.3,<3.0)
Requires-Dist: pydot (>=1.4.2,<2.0.0); extra == "animation"
Requires-Dist: tabulate (>=0.8.9,<0.9.0)
Requires-Dist: toolz (>=0.11,<0.12)
Project-URL: Documentation, https://stupidb.readthedocs.io
Project-URL: Repository, https://github.com/cpcloud/stupidb
